pyoutlineapi/__init__.py
pyoutlineapi/client.py
pyoutlineapi/exceptions.py
pyoutlineapi/models.py
pyoutlineapi-0.3.0.dist-info/LICENSE
pyoutlineapi-0.3.0.dist-info/METADATA
pyoutlineapi-0.3.0.dist-info/WHEEL
pyoutlineapi-0.3.0.dist-info/RECORD
