Metadata-Version: 2.3
Name: pyoutlineapi
Version: 0.3.0
Summary: A modern, async-first Python client for the Outline VPN Server API with comprehensive data validation through Pydantic models.
License: MIT
Keywords: outline,vpn,api,manager,wrapper,asyncio
Author: Denis Rozhnovskiy
Author-email: pytelemonbot@mail.ru
Requires-Python: >=3.10,<4.0
Classifier: Development Status :: 5 - Production/Stable
Classifier: Framework :: AsyncIO
Classifier: Framework :: Pydantic
Classifier: Framework :: aiohttp
Classifier: Intended Audience :: Developers
Classifier: License :: OSI Approved :: MIT License
Classifier: Operating System :: OS Independent
Classifier: Programming Language :: Python :: 3
Classifier: Programming Language :: Python :: 3.10
Classifier: Programming Language :: Python :: 3.11
Classifier: Programming Language :: Python :: 3.12
Classifier: Programming Language :: Python :: 3.13
Classifier: Programming Language :: Python :: 3 :: Only
Classifier: Topic :: Internet :: Proxy Servers
Classifier: Topic :: Internet :: WWW/HTTP :: HTTP Servers
Classifier: Topic :: Security
Classifier: Typing :: Typed
Requires-Dist: aiohttp (>=3.12.11,<4.0.0)
Requires-Dist: pydantic (>=2.11.5,<3.0.0)
Project-URL: Bug Tracker, https://github.com/orenlab/pyoutlineapi/issues
Project-URL: Documentation, https://orenlab.github.io/pyoutlineapi/
Project-URL: changelog, https://github.com/orenlab/pyoutlineapi/blob/main/CHANGELOG.md
Project-URL: documentation, https://orenlab.github.io/pyoutlineapi/
Project-URL: homepage, https://github.com/orenlab/pyoutlineapi
Project-URL: repository, https://github.com/orenlab/pyoutlineapi
